LICENSE
MANIFEST.in
README.rst
requirements.txt
setup.cfg
setup.py
src/si4ul/__init__.py
src/si4ul/changepoint_si.py
src/si4ul/kmeans_si.py
src/si4ul/segmentation_si.py
src/si4ul.egg-info/PKG-INFO
src/si4ul.egg-info/SOURCES.txt
src/si4ul.egg-info/dependency_links.txt
src/si4ul.egg-info/requires.txt
src/si4ul.egg-info/top_level.txt
src/si4ul/experiments/__init__.py
src/si4ul/experiments/changepoint_si.py
src/si4ul/experiments/kmeans_si.py
src/si4ul/experiments/segmentation_si.py
src/si4ul/plot/__init__.py
src/si4ul/plot/changepoint_si.py
src/si4ul/plot/kmeans_si.py
src/si4ul/plot/segmentation_si.py
src/si4ul/si/__init__.py
src/si4ul/si/changepoint_si.py
src/si4ul/si/kmeans_si.py
src/si4ul/si/segmentation_si.py
src/si4ul/si/sicore/__init__.py
src/si4ul/si/sicore/setup.py
src/si4ul/si/sicore/sicore/__init__.py
src/si4ul/si/sicore/sicore/cdf_approx.py
src/si4ul/si/sicore/sicore/cdf_mpmath.py
src/si4ul/si/sicore/sicore/evaluation.py
src/si4ul/si/sicore/sicore/figures.py
src/si4ul/si/sicore/sicore/intervals.py
src/si4ul/si/sicore/sicore/utils.py
src/si4ul/si/sicore/sicore/inference/__init__.py
src/si4ul/si/sicore/sicore/inference/base.py
src/si4ul/si/sicore/sicore/inference/norm.py
src/si4ul/si/sicore/sicore/inference/pci.py
src/si4ul/si/sicore/tests/__init__.py
src/si4ul/si/sicore/tests/conftest.py
src/si4ul/si/sicore/tests/test_cdf_approx.py
src/si4ul/si/sicore/tests/test_cdf_mpmath.py
src/si4ul/si/sicore/tests/test_evaluation.py
src/si4ul/si/sicore/tests/test_intervals.py
src/si4ul/si/sicore/tests/test_utils.py