Metadata-Version: 2.1
Name: si4ul
Version: 0.1.5
Summary: selective inference for unsupervised learning
Home-page: https://github.com/takeuchi-lab/si4ul
Author: Takeuchi Lab
Author-email: omori.y.mllabl.nit@gmail.com
License: MIT License
Platform: UNKNOWN
Classifier: Development Status :: 4 - Beta
Classifier: Programming Language :: Python :: 3
Classifier: Programming Language :: Python :: 3.9
Classifier: Topic :: Scientific/Engineering :: Artificial Intelligence
License-File: LICENSE
